utg_pkg/__init__.py
utg_pkg/cli.py
utg_pkg/generator.py
utg_pkg-0.1.1.dist-info/licenses/LICENSE
utg_pkg-0.1.1.dist-info/METADATA
utg_pkg-0.1.1.dist-info/WHEEL
utg_pkg-0.1.1.dist-info/entry_points.txt
utg_pkg-0.1.1.dist-info/top_level.txt
utg_pkg-0.1.1.dist-info/RECORD
