Metadata-Version: 2.4
Name: utg-pkg
Version: 0.1.1
Summary: Generate production-ready pytest unit tests.
Author-email: Gazal <2580gazal@gmail.com>
License: MIT
Requires-Python: >=3.8
License-File: LICENSE
Requires-Dist: python-dotenv
Requires-Dist: google-generativeai
Dynamic: license-file
